[{"timestamp":"2023-12-01T00:38:18.330Z","count":0,"uniques":0},{"timestamp":"2024-01-01T00:38:42.406Z","count":0,"uniques":0},{"timestamp":"2024-02-01T00:38:03.201Z","count":0,"uniques":0},{"timestamp":"2024-03-01T14:40:14.131Z","count":3,"uniques":1},{"timestamp":"2024-04-01T00:38:55.370Z","count":0,"uniques":0},{"timestamp":"2024-05-01T00:39:12.975Z","count":0,"uniques":0},{"timestamp":"2024-06-01T00:44:24.260Z","count":0,"uniques":0},{"timestamp":"2024-07-01T00:42:32.127Z","count":0,"uniques":0},{"timestamp":"2024-08-01T00:43:54.012Z","count":0,"uniques":0},{"timestamp":"2024-09-01T00:48:02.841Z","count":0,"uniques":0},{"timestamp":"2024-10-01T00:49:53.269Z","count":0,"uniques":0},{"timestamp":"2024-11-01T00:55:05.711Z","count":1,"uniques":1},{"timestamp":"2024-12-01T12:23:52.641Z","count":2,"uniques":2}]
