[{"timestamp":"2021-10-01T10:11:18.214Z","count":0,"uniques":0},{"timestamp":"2021-11-01T10:11:18.214Z","count":0,"uniques":0},{"timestamp":"2021-12-01T10:11:18.214Z","count":0,"uniques":0},{"timestamp":"2022-01-01T06:07:59.646Z","count":41,"uniques":8},{"timestamp":"2022-02-01T12:11:32.844Z","count":2,"uniques":2},{"timestamp":"2022-03-01T18:11:33.438Z","count":20,"uniques":6},{"timestamp":"2022-04-01T12:20:18.756Z","count":2,"uniques":2},{"timestamp":"2022-05-01T00:44:06.913Z","count":0,"uniques":0},{"timestamp":"2022-06-01T00:51:50.669Z","count":0,"uniques":0},{"timestamp":"2022-07-01T00:49:18.195Z","count":0,"uniques":0},{"timestamp":"2022-08-01T00:52:02.121Z","count":0,"uniques":0},{"timestamp":"2022-09-01T12:22:43.266Z","count":1,"uniques":1}]
