[{"timestamp":"2022-02-01T00:30:10.792Z","count":0,"uniques":0},{"timestamp":"2022-03-01T00:36:27.582Z","count":0,"uniques":0},{"timestamp":"2022-04-01T00:36:18.387Z","count":0,"uniques":0},{"timestamp":"2022-05-01T00:43:34.394Z","count":0,"uniques":0},{"timestamp":"2022-06-01T00:51:21.810Z","count":0,"uniques":0},{"timestamp":"2022-07-01T00:48:38.285Z","count":0,"uniques":0},{"timestamp":"2022-08-01T00:51:36.432Z","count":0,"uniques":0},{"timestamp":"2022-09-01T00:52:48.036Z","count":0,"uniques":0},{"timestamp":"2022-10-01T01:05:12.115Z","count":0,"uniques":0},{"timestamp":"2022-11-01T00:57:41.808Z","count":0,"uniques":0},{"timestamp":"2022-12-01T00:44:48.326Z","count":2,"uniques":1},{"timestamp":"2023-01-01T00:40:26.616Z","count":0,"uniques":0}]
